[
  {
    "name": "Productivity",
    "count": 137,
    "slug": "productivity"
  },
  {
    "name": "Developer Tools",
    "count": 87,
    "slug": "developer-tools"
  },
  {
    "name": "Utilities",
    "count": 54,
    "slug": "utilities"
  },
  {
    "name": "Photo & Video",
    "count": 30,
    "slug": "photo-video"
  },
  {
    "name": "Social Networking",
    "count": 30,
    "slug": "social-networking"
  },
  {
    "name": "Music",
    "count": 27,
    "slug": "music"
  },
  {
    "name": "Games",
    "count": 19,
    "slug": "games"
  },
  {
    "name": "Finance",
    "count": 10,
    "slug": "finance"
  },
  {
    "name": "Business",
    "count": 8,
    "slug": "business"
  },
  {
    "name": "Books",
    "count": 5,
    "slug": "books"
  },
  {
    "name": "Graphics & Design",
    "count": 5,
    "slug": "graphics-design"
  },
  {
    "name": "Education",
    "count": 4,
    "slug": "education"
  },
  {
    "name": "News",
    "count": 3,
    "slug": "news"
  },
  {
    "name": "Entertainment",
    "count": 2,
    "slug": "entertainment"
  },
  {
    "name": "Travel",
    "count": 1,
    "slug": "travel"
  },
  {
    "name": "Medical",
    "count": 1,
    "slug": "medical"
  }
]